traefik_certificate_exporter/__init__.py
traefik_certificate_exporter/_version.py
traefik_certificate_exporter/app.py
traefik_certificate_exporter/config_default.yaml
traefik_certificate_exporter/libs/certificate_exporter.py
traefik_certificate_exporter/libs/cli_args.py
traefik_certificate_exporter/libs/docker.py
traefik_certificate_exporter/libs/logging_utils.py
traefik_certificate_exporter/libs/object.py
traefik_certificate_exporter/libs/settings.py
traefik_certificate_exporter/logging.yaml
traefik_certificate_exporter-0.1.3.dist-info/LICENSE
traefik_certificate_exporter-0.1.3.dist-info/METADATA
traefik_certificate_exporter-0.1.3.dist-info/WHEEL
traefik_certificate_exporter-0.1.3.dist-info/entry_points.txt
traefik_certificate_exporter-0.1.3.dist-info/RECORD
