Metadata-Version: 2.1
Name: traefik-certificate-exporter
Version: 0.1.3
Summary: Watches for changes to traefik acme json files and extracts certificates to a specific folder
Home-page: https://github.com/ravensorb/traefik-certificate-exporter
Keywords: traefik,letsencrypt
Author: Shawn Anderson
Author-email: sanderson@eye-catcher.com
Requires-Python: >=3.10,<4.0
Classifier: Programming Language :: Python :: 3
Classifier: Programming Language :: Python :: 3.10
Classifier: Programming Language :: Python :: 3.11
Classifier: Programming Language :: Python :: 3.12
Requires-Dist: coloredlogs (>=15.0.1,<16.0.0)
Requires-Dist: confuse (>=2.0.1,<3.0.0)
Requires-Dist: docker (>=6.0.0,<7.0.0)
Requires-Dist: docker-pycreds (>=0.4.0,<0.5.0)
Requires-Dist: expandvars (>=0.12.0,<0.13.0)
Requires-Dist: importlib-resources (>=6.4.0,<7.0.0)
Requires-Dist: jsonpickle (>=3.0.3,<4.0.0)
Requires-Dist: logging-tree (>=1.9,<2.0)
Requires-Dist: poetry (>=1.8.2,<2.0.0)
Requires-Dist: python-dotenv (>=1.0.1,<2.0.0)
Requires-Dist: requests (>=2.28.1,<3.0.0)
Requires-Dist: watchdog (>=2.1.9,<3.0.0)
Project-URL: Repository, https://github.com/ravensorb/traefik-certificate-exporter
